{
    "goods":[
        {
            "name":"product1",
            "price":30,
            "URL":"http://111.com",
            "quantity":20, 
            "control":"Delete"
        },
        {
            "name":"product2",
            "price":40,
            "URL":"http://222.com",
            "quantity":70, 
            "control":"Delete"
        },
        {
            "name":"product3",
            "price":50,
            "URL":"http://333.com",
            "quantity":90, 
            "control":"Delete"
        },
        {
            "name":"product4",
            "price":80,
            "URL":"http://444.com",
            "quantity":60, 
            "control":"Delete"
        },
        {
            "name":"product5",
            "price":60,
            "URL":"http://111.com",
            "quantity":40, 
            "control":"Delete"
        },
        {
            "name":"product6",
            "price":80,
            "URL":"http://111.com",
            "quantity":55, 
            "control":"Delete"
        },
        {
            "name":"product7",
            "price":30,
            "URL":"http://111.com",
            "quantity":20, 
            "control":"Delete"
        }
    ]
}